more.content_security-0.2.0-py3.6-nspkg.pth
more/content_security/.gitignore
more/content_security/__init__.py
more/content_security/core.py
more/content_security/policy.py
more/content_security/tests/conftest.py
more/content_security/tests/test_app.py
more/content_security/tests/test_policy.py
more.content_security-0.2.0.dist-info/DESCRIPTION.rst
more.content_security-0.2.0.dist-info/METADATA
more.content_security-0.2.0.dist-info/RECORD
more.content_security-0.2.0.dist-info/WHEEL
more.content_security-0.2.0.dist-info/metadata.json
more.content_security-0.2.0.dist-info/namespace_packages.txt
more.content_security-0.2.0.dist-info/top_level.txt
