Metadata-Version: 2.0
Name: more.content-security
Version: 0.2.0
Summary: Content Security Policy for Morepath
Home-page: http://github.com/seantis/more.content_security
Author: Denis Krienbühl
Author-email: denis@href.ch
License: BSD
Platform: any
Classifier: Intended Audience :: Developers
Classifier: Programming Language :: Python
Classifier: Programming Language :: Python :: 3
Classifier: Topic :: Software Development :: Libraries :: Python Modules
Classifier: License :: OSI Approved :: BSD License
Requires-Dist: morepath
Provides-Extra: test
Requires-Dist: coverage; extra == 'test'
Requires-Dist: pytest; extra == 'test'
Requires-Dist: webtest; extra == 'test'
